CHANGES.txt
LICENSE.txt
MANIFEST.in
README
requirements.txt
setup.py
test_requirements.txt
sftpsyncer/__init__.py
sftpsyncer/exceptions.py
sftpsyncer/sftpagent.py
sftpsyncer.egg-info/PKG-INFO
sftpsyncer.egg-info/SOURCES.txt
sftpsyncer.egg-info/dependency_links.txt
sftpsyncer.egg-info/pbr.json
sftpsyncer.egg-info/requires.txt
sftpsyncer.egg-info/top_level.txt
sftpsyncer/test/__init__.py
sftpsyncer/test/test_main.py