Metadata-Version: 1.0
Name: sftpsyncer
Version: 0.1.9
Summary: Synchronise files between a local cache and an SFTP server
Home-page: http://bitbucket.org/dsms/sftpsyncher/
Author: Chris Horsley
Author-email: chris.horsley@csirtfoundry.com
License: LICENSE.txt
Platform: UNKNOWN
